Workbook
Name BUSINESS_TYPE_COLUMNS: #REF!
Name BUSS_TYPE_COLUMNS: #REF!
Name BUSS_TYPE_LISTS: #REF!
Name CA.R.2_Features_of_instruments_SUM: 'CA.R.2 Features of instruments'!$E$15:$T$15,'CA.R.2 Features of instruments'!$E$17:$T$17,'CA.R.2 Features of instruments'!$E$21:$T$21
Name checksum_F.LT.3: 'F.LT.3 TVOG'!$F$10:$I$26
Name DEV_MODE: #REF!
Name F.A.3B_End_Column_0: 'F.A.3B Qualitative Assessment'!$J$8
Name F.A.3B_Start_Column_0: 'F.A.3B Qualitative Assessment'!$D$8
Name FinancialMonth: #REF!
Name FinancialYear: #REF!
Name FORMULA_COLOR: #REF!
Name FORMULA_COLOR_SAMPLE: #REF!
Name INSURANCE_HEAD: #REF!
Name QDAP_Full_Columns: #REF!
Name QDAP_ON_OFF: #REF!
Name QDAP_WORKSHEETS: #REF!
Name ReportMonth: #REF!
Name ReportYearEndDate: #REF!
Name RULE_CAPG7A_C116: 'CA.P.G.7A_NatCat_Own_Scope'!$C$116
Name RULE_CAPG7A_D120D123: 'CA.P.G.7A_NatCat_Own_Scope'!$D$120:$D$123
Name RULE_CAPG7A_D125: 'CA.P.G.7A_NatCat_Own_Scope'!$D$125
Name RULE_CAPG7E_C96: 'CA.P.G.7E_NatCat_Own_YoYChange'!$C$96
Name RULE_CAPG7E_C97: 'CA.P.G.7E_NatCat_Own_YoYChange'!$C$97
Name RULE_CAPLT2_I3014I3021: 'CA.P.LT.2 HRG'!$I$3014:$I$3021
Name RULE_CAPLT2_J3014J3021: 'CA.P.LT.2 HRG'!$J$3014:$J$3021
Name RULE_CAPLT3_J3014J3023: 'CA.P.LT.3 Product'!$J$3014:$J$3023
Name RULE_CAPLT3_K3014K3023: 'CA.P.LT.3 Product'!$K$3014:$K$3023
Name RULE_CAPLT4_G26: 'CA.P.LT.4 HRGvsProduct'!$G$26
Name RULE_DATE_O18: 'F.A.6A Port Inv of Port Inv'!$O$18:$O$24
Name RULE_DATE_S18: 'F.A.6 Port Inv'!$S$18:$S$29
Name RULE_DATE_T18: 'F.A.6 Port Inv'!$T$18:$T$29
Name RULE_F3_C35F35: 'F.3 AOM'!$C$35:$F$35
Name RULE_F3_C36F36: 'F.3 AOM'!$C$36:$F$36
Name RULE_F3_C38F38: 'F.3 AOM'!$C$38:$F$38
Name RULE_F3_C39F39: 'F.3 AOM'!$C$39:$F$39
Name RULE_F3_F35: 'F.3 AOM'!$F$35
Name RULE_F3_F36: 'F.3 AOM'!$F$36
Name RULE_FA4_G7576: 'F.A.4 Derivatives'!$G$75:$G$76
Name RULE_FA4_S1160: 'F.A.4 Derivatives'!$S$11:$S$60
Name RULE_FA4_T6569: 'F.A.4 Derivatives'!$T$65:$T$69
Name RULE_FA4_U6569: 'F.A.4 Derivatives'!$U$65:$U$69
Name RULE_FA6_AE29: 'F.A.6 Port Inv'!$AE$29
Name RULE_FA6_H33: 'F.A.6 Port Inv'!$H$33
Name RULE_FA6_H34: 'F.A.6 Port Inv'!$H$34
Name RULE_FA6_H35: 'F.A.6 Port Inv'!$H$35
Name RULE_FA6_I34: 'F.A.6 Port Inv'!$I$34
Name RULE_FA6_I35: 'F.A.6 Port Inv'!$I$35
Name RULE_FA6_M18M27: 'F.A.6 Port Inv'!$M$18:$M$27
Name RULE_FA6_U29: 'F.A.6 Port Inv'!$U$29
Name RULE_FA6_V29: 'F.A.6 Port Inv'!$V$29
Name RULE_FA6_W29: 'F.A.6 Port Inv'!$W$29
Name RULE_FA6_X29: 'F.A.6 Port Inv'!$X$29
Name RULE_FA6_Y29: 'F.A.6 Port Inv'!$Y$29
Name RULE_FA6A_G28: 'F.A.6A Port Inv of Port Inv'!$G$28
Name RULE_FA6A_G29: 'F.A.6A Port Inv of Port Inv'!$G$29
Name RULE_FA6A_G30: 'F.A.6A Port Inv of Port Inv'!$G$30
Name RULE_FA6A_H30: 'F.A.6A Port Inv of Port Inv'!$H$30
Name RULE_FA7_N1016: 'F.A.7 Related Parties'!$N$10:$N$16
Name RULE_FA7_O1016: 'F.A.7 Related Parties'!$O$10:$O$16
Name RULE_FT6_C85I85: 'F.LT.6 Par Business'!$C$85:$I$85

Sheet F.1 EBS
A1: F.1 Regulatory balance sheet
A2: Name of Insurer: | B2: ='Cover Page'!F15
A3: Valuation Date: | B3: 31 Dec 2025
A4: Reporting Period:
A7: (Unit: in HKD thousands) | H7: Long term offshore reinsurance business | J7: General offshore reinsurance business
D8: For branch operating in Hong Kong (other than a designated insurer), whether offshore reinsurance fund is established?
A11: Column 1 | B11: Column 2 | C11: Column 3 | D11: Column 4 | E11: Column 5 | F11: Column 6 | G11: Column 7 | H11: Column 8 | I11: Column 9 | J11: Column 10 | K11: Column 11 | L11: Column 12 | N11: Column 13 | O11: Column 14 | P11: Column 15 | Q11: Column 16 | R11: Column 17 | S11: Column 18 | T11: Column 19 | U11: Column 20 | W11: Column 21 | X11: Column 22 | Z11: Column 23 | AA11: Column 24 | AB11: Column 25 | AC11: Column 26 | AD11: Column 27 | AE11: Column 28 | AF11: Column 29 | AG11: Column 30 | AH11: Column 31 | AI11: Column 32 | AJ11: Column 33
A12: Asset / Liability / Capital Items | B12: (a) | C12: (b) | D12: (c) | E12: (d) | F12: (e) | G12: (f) | H12: (g) | I12: (h) | J12: (i) | K12: (j) | L12: (k) | N12: (l) | O12: (m) | P12: (n) | Q12: (o) | R12: (p) | S12: (q) | T12: (r) | U12: (s) | W12: (t) | X12: (u) | Z12: (v) | AA12: (w) | AB12: (x) | AC12: (w) | AD12: (x) | AE12: (y) | AF12: (z) | AG12: (aa) | AH12: (ab) | AI12: (ac) | AJ12: (ad)
B13: Carrying values under scope of regulatory consolidation | C13: Carrying values under scope of regulatory consolidation | W13: Carrying values under scope of regulatory consolidation | Z13: General Insurance Liabilities breakdown for public disclosure
C14: Long Term Insurance Business | I14: General Insurance Business | K14: Non-insurance operations | L14: Shareholder Fund | N14: Applicable to HK insurers or designated insurers: Of which belongs to Branch insurance operations outside Hong Kong (Please fill in the jurisdiction of each branch operation outside Hong Kong in the row below) | W14: Total Long Term Insurance Business | X14: Total General Insurance Business | AA14: Direct | AH14: Reinsurance | AJ14: Total
C15: HK insurers or designated insurers: all long term insurance business Branch operating in Hong Kong: all long term insurance business, other than offshore RI business if offshore RI fund is established | H15: Applicable to branch operating in Hong Kong with offshore RI fund established: Offshore RI business related | I15: HK insurers or designated insurers: all general insurance business Branch operating in Hong Kong: all general insurance business, other than offshore RI business if offshore RI fund is established | J15: Applicable to branch operating in Hong Kong with offshore RI fund established: Offshore RI business related | N15: (Jurisdiction) Branch 1 | P15: (Jurisdiction) Branch 2 | R15: (Jurisdiction) Branch 3 | T15: (Jurisdiction) Branch 4 | AA15: Accident & Health | AB15: Motor Vehicle | AC15: Marine, Aviation, and Transport | AD15: Property Damage | AE15: Employees' Compensation | AF15: General Liability | AG15: Pecuniary Loss | AH15: Proportional | AI15: Non-Proportional
C16: Linked Long Term (Class C) | D16: Retirement scheme category I (Class G) | E16: Retirement scheme category II (Class H) | F16: Participating Business | G16: Other Businesses | N16: Total carrying values of the branch | O16: Of which belongs to Long Term Fund | P16: Total carrying values of the branch | Q16: Of which belongs to Long Term Fund | R16: Total carrying values of the branch | S16: Of which belongs to Long Term Fund | T16: Total carrying values of the branch | U16: Of which belongs to Long Term Fund
A17: Description | B17: As at the end of reporting period | N17: As at the end of reporting period
B18: (T)
A19: I – Total assets | Z19: Gross Outstanding Claims Liabilities excluding MOCE | AA19: ='F.G.1_ClaimLiab'!C12+'F.G.1_ClaimLiab'!C29-AA20 | AB19: ='F.G.1_ClaimLiab'!C13+'F.G.1_ClaimLiab'!C30-AB20 | AC19: =SUM('F.G.1_ClaimLiab'!C14:C16,'F.G.1_ClaimLiab'!C31:C33)-AC20 | AD19: ='F.G.1_ClaimLiab'!C17+'F.G.1_ClaimLiab'!C34-AD20 | AE19: ='F.G.1_ClaimLiab'!C18+'F.G.1_ClaimLiab'!C35-AE20 | AF19: ='F.G.1_ClaimLiab'!C21+'F.G.1_ClaimLiab'!C38-AF20 | AG19: ='F.G.1_ClaimLiab'!C24+'F.G.1_ClaimLiab'!C41-AG20 | AH19: ='F.G.1_ClaimLiab'!C46+'F.G.1_ClaimLiab'!C60+'F.G.1_ClaimLiab'!C96+'F.G.1_ClaimLiab'!C110-AH20 | AI19: ='F.G.1_ClaimLiab'!C74+'F.G.1_ClaimLiab'!C85+'F.G.1_ClaimLiab'!C124+'F.G.1_ClaimLiab'!C135-AI20 | AJ19: =SUM(AA19:AI19)
A20: I.A. Goodwill | Z20: Gross Outstanding Claims Liabilities MOCE | AA20: ='F.G.1_ClaimLiab'!J12+'F.G.1_ClaimLiab'!J29 | AB20: ='F.G.1_ClaimLiab'!J13+'F.G.1_ClaimLiab'!J30 | AC20: =SUM('F.G.1_ClaimLiab'!J14:J16,'F.G.1_ClaimLiab'!J31:J33) | AD20: ='F.G.1_ClaimLiab'!J17+'F.G.1_ClaimLiab'!J34 | AE20: ='F.G.1_ClaimLiab'!J18+'F.G.1_ClaimLiab'!J35 | AF20: ='F.G.1_ClaimLiab'!J21+'F.G.1_ClaimLiab'!J38 | AG20: ='F.G.1_ClaimLiab'!J24+'F.G.1_ClaimLiab'!J41 | AH20: ='F.G.1_ClaimLiab'!J46+'F.G.1_ClaimLiab'!J60+'F.G.1_ClaimLiab'!J96+'F.G.1_ClaimLiab'!J110 | AI20: ='F.G.1_ClaimLiab'!J74+'F.G.1_ClaimLiab'!J85+'F.G.1_ClaimLiab'!J124+'F.G.1_ClaimLiab'!J135 | AJ20: =SUM(AA20:AI20)
A21: I.B. Intangible assets | Z21: Gross Premium Liabilities excluding MOCE | AA21: ='F.G.2_PL'!C12+'F.G.2_PL'!C29-AA22 | AB21: ='F.G.2_PL'!C13+'F.G.2_PL'!C30-AB22 | AC21: =SUM('F.G.2_PL'!C14:C16,'F.G.2_PL'!C31:C33)-AC22 | AD21: ='F.G.2_PL'!C17+'F.G.2_PL'!C34-AD22 | AE21: ='F.G.2_PL'!C18+'F.G.2_PL'!C35-AE22 | AF21: ='F.G.2_PL'!C21+'F.G.2_PL'!C38-AF22 | AG21: ='F.G.2_PL'!C24+'F.G.2_PL'!C41-AG22 | AH21: ='F.G.2_PL'!C46+'F.G.2_PL'!C60+'F.G.2_PL'!C96+'F.G.2_PL'!C110-AH22 | AI21: ='F.G.2_PL'!C74+'F.G.2_PL'!C85+'F.G.2_PL'!C124+'F.G.2_PL'!C135-AI22 | AJ21: =SUM(AA21:AI21)
A22: I.C. Cash and cash equivalents, and statutory deposits | B22: 2850 | C22: =SUM(C23:C24) | D22: =SUM(D23:D24) | E22: =SUM(E23:E24) | F22: =SUM(F23:F24) | G22: =SUM(G23:G24) | H22: =SUM(H23:H24) | I22: =SUM(I23:I24) | J22: =SUM(J23:J24) | ... L22: =SUM(L23:L24) | N22: =SUM(N23:N24) | P22: =SUM(P23:P24) | R22: =SUM(R23:R24) | T22: =SUM(T23:T24) | W22: =SUM(C22:H22) | X22: =SUM(I22:J22) | Z22: Gross Premium Liabilities MOCE | AA22: ='F.G.2A_PL_Recog'!K12+'F.G.2A_PL_Recog'!K29+'F.G.2B_PL_notRecog'!K12+'F.G.2B_PL_notRecog'!K29 | AB22: ='F.G.2A_PL_Recog'!K13+'F.G.2A_PL_Recog'!K30+'F.G.2B_PL_notRecog'!K13+'F.G.2B_PL_notRecog'!K30 | AC22: =SUM('F.G.2A_PL_Recog'!K14:K16,'F.G.2A_PL_Recog'!K31:K33)+SUM('F.G.2B_PL_notRecog'!K14:K16,'F.G.2B_PL_notRecog'!K31:K33) | AD22: ='F.G.2A_PL_Recog'!K17+'F.G.2A_PL_Recog'!K34+'F.G.2B_PL_notRecog'!K17+'F.G.2B_PL_notRecog'!K34 | AE22: ='F.G.2A_PL_Recog'!K18+'F.G.2A_PL_Recog'!K35+'F.G.2B_PL_notRecog'!K18+'F.G.2B_PL_notRecog'!K35 | AF22: ='F.G.2A_PL_Recog'!K21+'F.G.2A_PL_Recog'!K38+'F.G.2B_PL_notRecog'!K21+'F.G.2B_PL_notRecog'!K38 | AG22: ='F.G.2A_PL_Recog'!K24+'F.G.2A_PL_Recog'!K41+'F.G.2B_PL_notRecog'!K24+'F.G.2B_PL_notRecog'!K41 | AH22: ='F.G.2A_PL_Recog'!K46+'F.G.2A_PL_Recog'!K60+'F.G.2A_PL_Recog'!K96+'F.G.2A_PL_Recog'!K110+'F.G.2B_PL_notRecog'!K46+'F.G.2B_PL_notRecog'!K60+'F.G.2B_PL_notRecog'!K96+'F.G.2B_PL_notRecog'!K110 | AI22: ='F.G.2A_PL_Recog'!K74+'F.G.2A_PL_Recog'!K85+'F.G.2A_PL_Recog'!K124+'F.G.2A_PL_Recog'!K135+'F.G.2B_PL_notRecog'!K74+'F.G.2B_PL_notRecog'!K85+'F.G.2B_PL_notRecog'!K124+'F.G.2B_PL_notRecog'!K135 | AJ22: =SUM(AA22:AI22)
A23: I.C1. Statutory deposits | B23: 1200 | W23: =SUM(C23:H23) | X23: =SUM(I23:J23) | Z23: Gross General insurance liabilities excluding 'Other General Insurance Liabilties' | AA23: =SUM(AA19:AA22) | AB23: =SUM(AB19:AB22) | AC23: =SUM(AC19:AC22) | AD23: =SUM(AD19:AD22) | AE23: =SUM(AE19:AE22) | AF23: =SUM(AF19:AF22) | AG23: =SUM(AG19:AG22) | AH23: =SUM(AH19:AH22) | AI23: =SUM(AI19:AI22) | AJ23: =SUM(AA23:AI23)
A24: I.C2. Non-statutory or other deposits | B24: 1650 | W24: =SUM(C24:H24) | X24: =SUM(I24:J24) | Z24: Net General insurance liabilities excluding 'Other General Insurance Liabilties' | AA24: ='F.G.1_ClaimLiab'!E12+'F.G.1_ClaimLiab'!E29+'F.G.2_PL'!E12+'F.G.2_PL'!E29 | AB24: ='F.G.1_ClaimLiab'!E13+'F.G.1_ClaimLiab'!E30+'F.G.2_PL'!E13+'F.G.2_PL'!E30 | AC24: =SUM('F.G.1_ClaimLiab'!E14:E16,'F.G.1_ClaimLiab'!E31:E33)+SUM('F.G.2_PL'!E14:E16,'F.G.2_PL'!E31:E33) | AD24: ='F.G.1_ClaimLiab'!E17+'F.G.1_ClaimLiab'!E34+'F.G.2_PL'!E17+'F.G.2_PL'!E34 | AE24: ='F.G.1_ClaimLiab'!E18+'F.G.1_ClaimLiab'!E35+'F.G.2_PL'!E18+'F.G.2_PL'!E35 | AF24: ='F.G.1_ClaimLiab'!E21+'F.G.1_ClaimLiab'!E38+'F.G.2_PL'!E21+'F.G.2_PL'!E38 | AG24: ='F.G.1_ClaimLiab'!E24+'F.G.1_ClaimLiab'!E41+'F.G.2_PL'!E24+'F.G.2_PL'!E41 | AH24: ='F.G.1_ClaimLiab'!E46+'F.G.1_ClaimLiab'!E60+'F.G.1_ClaimLiab'!E96+'F.G.1_ClaimLiab'!E110+'F.G.2_PL'!E46+'F.G.2_PL'!E60+'F.G.2_PL'!E96+'F.G.2_PL'!E110 | AI24: ='F.G.1_ClaimLiab'!E74+'F.G.1_ClaimLiab'!E85+'F.G.1_ClaimLiab'!E124+'F.G.1_ClaimLiab'!E135+'F.G.2_PL'!E74+'F.G.2_PL'!E85+'F.G.2_PL'!E124+'F.G.2_PL'!E135 | AJ24: =SUM(AA24:AI24)
A25: I.D. Deposits with original maturity more than three months | B25: =SUM(C25:L25) | W25: =SUM(C25:H25) | X25: =SUM(I25:J25) | Z25: Net General insurance liabilities | AJ25: =AJ24+B87
A26: I.E. Debt securities | B26: 28400 | C26: =SUM(C27:C32) | D26: =SUM(D27:D32) | E26: =SUM(E27:E32) | F26: =SUM(F27:F32) | G26: =SUM(G27:G32) | H26: =SUM(H27:H32) | I26: =SUM(I27:I32) | J26: =SUM(J27:J32) | ... L26: =SUM(L27:L32) | N26: =SUM(N27:N32) | P26: =SUM(P27:P32) | R26: =SUM(R27:R32) | T26: =SUM(T27:T32) | W26: =SUM(C26:H26) | X26: =SUM(I26:J26)
A27: I.E1. Sovereign issued | B27: 6200 | W27: =SUM(C27:H27) | X27: =SUM(I27:J27)
A28: I.E2. Issued by domestic public sector entity and other public sector entity fully guaranteed by government or central banks | B28: =SUM(C28:L28) | W28: =SUM(C28:H28) | X28: =SUM(I28:J28)
A29: I.E3. Corporate issued | B29: 19500 | W29: =SUM(C29:H29) | X29: =SUM(I29:J29)
A30: I.E4. Asset backed securities | B30: 1800 | W30: =SUM(C30:H30) | X30: =SUM(I30:J30)
A31: I.E5. Other structured securities | B31: =SUM(C31:L31) | W31: =SUM(C31:H31) | X31: =SUM(I31:J31)
A32: I.E6. Other debt securities | B32: 900 | W32: =SUM(C32:H32) | X32: =SUM(I32:J32)
A33: I.F. Equities | B33: 920 | C33: =SUM(C34:C38) | D33: =SUM(D34:D38) | E33: =SUM(E34:E38) | F33: =SUM(F34:F38) | G33: =SUM(G34:G38) | H33: =SUM(H34:H38) | I33: =SUM(I34:I38) | J33: =SUM(J34:J38) | ... L33: =SUM(L34:L38) | N33: =SUM(N34:N38) | P33: =SUM(P34:P38) | R33: =SUM(R34:R38) | T33: =SUM(T34:T38) | W33: =SUM(C33:H33) | X33: =SUM(I33:J33)
A34: I.F1. Listed equities | B34: 920 | W34: =SUM(C34:H34) | X34: =SUM(I34:J34)
A35: I.F2. Unlisted or private equities | B35: =SUM(C35:L35) | W35: =SUM(C35:H35) | X35: =SUM(I35:J35)
A36: I.F3. Portfolio Investment | B36: =SUM(C36:L36) | W36: =SUM(C36:H36) | X36: =SUM(I36:J36)
A37: I.F4. Hybrid equities and preference equities | B37: =SUM(C37:L37) | W37: =SUM(C37:H37) | X37: =SUM(I37:J37)
A38: I.F5. Strategic investments | B38: =SUM(C38:L38) | W38: =SUM(C38:H38) | X38: =SUM(I38:J38)
A39: I.G. Derivative financial instruments | B39: =SUM(C39:L39) | W39: =SUM(C39:H39) | X39: =SUM(I39:J39)
A40: I.H. Properties | B40: =SUM(B41:B42) | C40: =SUM(C41:C42) | D40: =SUM(D41:D42) | E40: =SUM(E41:E42) | F40: =SUM(F41:F42) | G40: =SUM(G41:G42) | H40: =SUM(H41:H42) | I40: =SUM(I41:I42) | ... L40: =SUM(L41:L42) | N40: =SUM(N41:N42) | P40: =SUM(P41:P42) | R40: =SUM(R41:R42) | T40: =SUM(T41:T42) | W40: =SUM(C40:H40) | X40: =SUM(I40:J40)
A41: I.H1. Investment properties | B41: =SUM(C41:L41) | W41: =SUM(C41:H41) | X41: =SUM(I41:J41)
A42: I.H2. Own-occupied properties | B42: =SUM(C42:L42) | W42: =SUM(C42:H42) | X42: =SUM(I42:J42)
A43: I.I. Policyholder account assets in respect of unit-linked products / account value for retirement scheme | B43: =SUM(C43:L43) | W43: =SUM(C43:H43)
A44: I.J. Loans and advances | B44: 1150 | C44: =SUM(C45:C46) | D44: =SUM(D45:D46) | E44: =SUM(E45:E46) | F44: =SUM(F45:F46) | G44: =SUM(G45:G46) | H44: =SUM(H45:H46) | I44: =SUM(I45:I46) | J44: =SUM(J45:J46) | ... L44: =SUM(L45:L46) | N44: =SUM(N45:N46) | P44: =SUM(P45:P46) | R44: =SUM(R45:R46) | T44: =SUM(T45:T46) | W44: =SUM(C44:H44) | X44: =SUM(I44:J44)
A45: I.J1. Policy loans | B45: =SUM(C45:L45) | W45: =SUM(C45:H45) | X45: =SUM(I45:J45)
A46: I.J2. Loans and advances other than policy loans | B46: =SUM(C46:L46) | W46: =SUM(C46:H46) | X46: =SUM(I46:J46)
A47: I.K. Reverse repurchase agreements | B47: =SUM(C47:L47) | W47: =SUM(C47:H47) | X47: =SUM(I47:J47)
A48: I.L Subsidiaries | B48: =SUM(B49:B50) | C48: =SUM(C49:C50) | D48: =SUM(D49:D50) | E48: =SUM(E49:E50) | F48: =SUM(F49:F50) | G48: =SUM(G49:G50) | H48: =SUM(H49:H50) | I48: =SUM(I49:I50) | ... L48: =SUM(L49:L50) | N48: =SUM(N49:N50) | P48: =SUM(P49:P50) | R48: =SUM(R49:R50) | T48: =SUM(T49:T50) | W48: =SUM(C48:H48) | X48: =SUM(I48:J48)
A49: I.L1. Of which: amounts due from | B49: =SUM(C49:L49) | W49: =SUM(C49:H49) | X49: =SUM(I49:J49)
A50: I.L2. Of which: investment in | B50: =SUM(C50:L50) | W50: =SUM(C50:H50) | X50: =SUM(I50:J50)
A51: I.M Affiliates / associates | B51: =SUM(B52:B53) | C51: =SUM(C52:C53) | D51: =SUM(D52:D53) | E51: =SUM(E52:E53) | F51: =SUM(F52:F53) | G51: =SUM(G52:G53) | H51: =SUM(H52:H53) | I51: =SUM(I52:I53) | ... L51: =SUM(L52:L53) | N51: =SUM(N52:N53) | P51: =SUM(P52:P53) | R51: =SUM(R52:R53) | T51: =SUM(T52:T53) | W51: =SUM(C51:H51) | X51: =SUM(I51:J51)
A52: I.M1. Of which: amounts due from | B52: =SUM(C52:L52) | W52: =SUM(C52:H52) | X52: =SUM(I52:J52)
A53: I.M2. Of which: investment in | B53: =SUM(C53:L53) | W53: =SUM(C53:H53) | X53: =SUM(I53:J53)
A54: I.N Fellow subsidiaries | B54: =SUM(B55:B56) | C54: =SUM(C55:C56) | D54: =SUM(D55:D56) | E54: =SUM(E55:E56) | F54: =SUM(F55:F56) | G54: =SUM(G55:G56) | H54: =SUM(H55:H56) | I54: =SUM(I55:I56) | ... L54: =SUM(L55:L56) | N54: =SUM(N55:N56) | P54: =SUM(P55:P56) | R54: =SUM(R55:R56) | T54: =SUM(T55:T56) | W54: =SUM(C54:H54) | X54: =SUM(I54:J54)
A55: I.N1. Of which: amounts due from | B55: =SUM(C55:L55) | W55: =SUM(C55:H55) | X55: =SUM(I55:J55)
A56: I.N2. Of which: investment in | B56: =SUM(C56:L56) | W56: =SUM(C56:H56) | X56: =SUM(I56:J56)
A57: I.O Amount due from holding company | B57: =SUM(C57:L57) | W57: =SUM(C57:H57) | X57: =SUM(I57:J57)
A58: I.OA Amount due from Head Office | B58: =SUM(C58:L58) | W58: =SUM(C58:H58) | X58: =SUM(I58:J58)
A59: I.P. Reinsurance assets | B59: 10650 | W59: =SUM(C59:H59) | X59: =SUM(I59:J59)
A60: I.Q. Non-investment assets | B60: 980 | C60: =SUM(C61,C65:C72) | D60: =SUM(D61,D65:D72) | E60: =SUM(E61,E65:E72) | F60: =SUM(F61,F65:F72) | G60: =SUM(G61,G65:G72) | H60: =SUM(H61,H65:H72) | I60: =SUM(I61,I65:I72) | J60: =SUM(J61,J65:J72) | ... L60: =SUM(L61,L65:L72) | N60: =SUM(N61,N65:N72) | P60: =SUM(P61,P65:P72) | R60: =SUM(R61,R65:R72) | T60: =SUM(T61,T65:T72) | W60: =SUM(C60:H60) | X60: =SUM(I60:J60)
A61: I.Q1. Receivables arising from insurance operations | B61: 650 | C61: =SUM(C62:C64) | D61: =SUM(D62:D64) | E61: =SUM(E62:E64) | F61: =SUM(F62:F64) | G61: =SUM(G62:G64) | H61: =SUM(H62:H64) | I61: =SUM(I62:I64) | J61: =SUM(J62:J64) | N61: =SUM(N62:N64) | P61: =SUM(P62:P64) | R61: =SUM(R62:R64) | T61: =SUM(T62:T64) | W61: =SUM(C61:H61) | X61: =SUM(I61:J61)
A62: I.Q1a. policyholders | B62: 220 | W62: =SUM(C62:H62) | X62: =SUM(I62:J62)
A63: I.Q1b. intermediaries | B63: 180 | W63: =SUM(C63:H63) | X63: =SUM(I63:J63)
A64: I.Q1c. reinsurers | B64: 250 | W64: =SUM(C64:H64) | X64: =SUM(I64:J64)
A65: I.Q2. Investment income receivable from financial assets | B65: =SUM(C65:L65) | W65: =SUM(C65:H65) | X65: =SUM(I65:J65)
A66: I.Q3. Other property, plant and equipment (excluding properties) | B66: 200 | W66: =SUM(C66:H66) | X66: =SUM(I66:J66)
A67: I.Q4. Current tax assets | B67: =SUM(C67:L67) | W67: =SUM(C67:H67) | X67: =SUM(I67:J67)
A68: I.Q5. Deferred tax assets | B68: 80 | W68: =SUM(C68:H68) | X68: =SUM(I68:J68)
A69: I.Q6. Direct investment in Own Capital instruments | B69: =SUM(C69:L69) | W69: =SUM(C69:H69) | X69: =SUM(I69:J69)
A70: I.Q7. Defined benefit pension fund assets | B70: =SUM(C70:L70) | W70: =SUM(C70:H70) | X70: =SUM(I70:J70)
A71: I.Q8. Lease receivables / right-of-use assets | B71: =SUM(C71:L71) | W71: =SUM(C71:H71) | X71: =SUM(I71:J71)
A72: I.Q9. Other non-investment assets | B72: 50 | W72: =SUM(C72:H72) | X72: =SUM(I72:J72)
A73: I.R.Amount due from Shareholder Fund | W73: =SUM(C73:H73) | X73: =SUM(I73:J73)
A74: I.S.Amount due from other insurance funds | W74: =SUM(C74:H74) | X74: =SUM(I74:J74)
A75: I.T. [Any other assets, not elsewhere shown] | B75: =SUM(C75:L75) | W75: =SUM(C75:H75) | X75: =SUM(I75:J75)
A77: I.U. Total assets (summation of items I.A. to I.T.) | B77: 45000 | C77: =SUM(C20:C22,C25:C26,C33,C39:C40,C43:C44,C47:C48,C51,C54,C57:C60,C73:C75) | D77: =SUM(D20:D22,D25:D26,D33,D39:D40,D43:D44,D47:D48,D51,D54,D57:D60,D73:D75) | E77: =SUM(E20:E22,E25:E26,E33,E39:E40,E43:E44,E47:E48,E51,E54,E57:E60,E73:E75) | F77: =SUM(F20:F22,F25:F26,F33,F39:F40,F43:F44,F47:F48,F51,F54,F57:F60,F73:F75) | G77: =SUM(G20:G22,G25:G26,G33,G39:G40,G43:G44,G47:G48,G51,G54,G57:G60,G73:G75) | H77: =SUM(H20:H22,H25:H26,H33,H39:H40,H43:H44,H47:H48,H51,H54,H57:H60,H73:H75) | I77: =SUM(I20:I22,I25:I26,I33,I39:I40,I43:I44,I47:I48,I51,I54,I57:I60,I73:I75) | J77: =SUM(J20:J22,J25:J26,J33,J39:J40,J43:J44,J47:J48,J51,J54,J57:J60,J73:J75) | ... L77: =SUM(L20:L22,L25:L26,L33,L39:L40,L43:L44,L47:L48,L51,L54,L57:L60,L73:L75) | N77: =SUM(N20:N22,N25:N26,N33,N39:N40,N43:N44,N47:N48,N51,N54,N57:N60,N73:N75) | O77: =SUM(O20:O22,O25:O26,O33,O39:O40,O43:O44,O47:O48,O51,O54,O57:O60,O73:O75) | P77: =SUM(P20:P22,P25:P26,P33,P39:P40,P43:P44,P47:P48,P51,P54,P57:P60,P73:P75) | Q77: =SUM(Q20:Q22,Q25:Q26,Q33,Q39:Q40,Q43:Q44,Q47:Q48,Q51,Q54,Q57:Q60,Q73:Q75) | R77: =SUM(R20:R22,R25:R26,R33,R39:R40,R43:R44,R47:R48,R51,R54,R57:R60,R73:R75) | S77: =SUM(S20:S22,S25:S26,S33,S39:S40,S43:S44,S47:S48,S51,S54,S57:S60,S73:S75) | T77: =SUM(T20:T22,T25:T26,T33,T39:T40,T43:T44,T47:T48,T51,T54,T57:T60,T73:T75) | U77: =SUM(U20:U22,U25:U26,U33,U39:U40,U43:U44,U47:U48,U51,U54,U57:U60,U73:U75) | W77: =SUM(C77:H77) | X77: =SUM(I77:J77)
A79: II – Total liabilities
A80: II.A. and II.B. Total insurance liabilities (gross of reinsurance) | B80: 27650 | C80: =SUM(C81,C88) | D80: =SUM(D81,D88) | E80: =SUM(E81,E88) | F80: =SUM(F81,F88) | G80: =SUM(G81,G88) | H80: =SUM(H81,H88) | I80: =SUM(I81,I88) | J80: =SUM(J81,J88) | ... L80: =SUM(L81,L88) | N80: =SUM(N81,N88) | O80: =SUM(O81,O88) | P80: =SUM(P81,P88) | Q80: =SUM(Q81,Q88) | R80: =SUM(R81,R88) | S80: =SUM(S81,S88) | T80: =SUM(T81,T88) | U80: =SUM(U81,U88) | W80: =SUM(C80:H80) | X80: =SUM(I80:J80)
A81: Of which: II.A. General insurance liabilities | B81: =SUM(B82:B84,B87) | C81: =SUM(C82:C84,C87) | F81: =SUM(F82:F84,F87) | G81: =SUM(G82:G84,G87) | H81: =SUM(H82:H84,H87) | I81: =SUM(I82:I84,I87) | J81: =SUM(J82:J84,J87) | N81: =SUM(N82:N84,N87) | O81: =SUM(O82:O84,O87) | P81: =SUM(P82:P84,P87) | Q81: =SUM(Q82:Q84,Q87) | R81: =SUM(R82:R84,R87) | S81: =SUM(S82:S84,S87) | T81: =SUM(T82:T84,T87) | U81: =SUM(U82:U84,U87) | W81: =SUM(C81:H81) | X81: =SUM(I81:J81)
A82: II.A1. Outstanding claims liabilities | B82: =SUM(C82:L82) | W82: =SUM(C82:H82) | X82: =SUM(I82:J82)
A83: II.A2. Premium liabilities | B83: =SUM(C83:L83) | W83: =SUM(C83:H83) | X83: =SUM(I83:J83)
A84: II.A3. Margin over Current Estimate for: | B84: =SUM(B85:B86) | C84: =SUM(C85:C86) | F84: =SUM(F85:F86) | G84: =SUM(G85:G86) | H84: =SUM(H85:H86) | I84: =SUM(I85:I86) | J84: =SUM(J85:J86) | N84: =SUM(N85:N86) | O84: =SUM(O85:O86) | P84: =SUM(P85:P86) | Q84: =SUM(Q85:Q86) | R84: =SUM(R85:R86) | S84: =SUM(S85:S86) | T84: =SUM(T85:T86) | U84: =SUM(U85:U86) | W84: =SUM(C84:H84) | X84: =SUM(I84:J84)
A85: II.A3a. Outstanding claims liabilities | B85: =SUM(C85:L85) | W85: =SUM(C85:H85) | X85: =SUM(I85:J85)
A86: II.A3b. Premium liabilities | B86: =SUM(C86:L86) | W86: =SUM(C86:H86) | X86: =SUM(I86:J86)
A87: II.A4. Other general insurance liabilities | B87: =SUM(C87:L87) | W87: =SUM(C87:H87) | X87: =SUM(I87:J87)
A88: Of which: II.B Long term insurance liabilities | B88: =SUM(B89:B94) | C88: =SUM(C89:C94) | D88: =SUM(D89:D94) | E88: =SUM(E89:E94) | F88: =SUM(F89:F94) | G88: =SUM(G89:G94) | H88: =SUM(H89:H94) | N88: =SUM(N89:N94) | O88: =SUM(O89:O94) | P88: =SUM(P89:P94) | Q88: =SUM(Q89:Q94) | R88: =SUM(R89:R94) | S88: =SUM(S89:S94) | T88: =SUM(T89:T94) | U88: =SUM(U89:U94) | W88: =SUM(C88:H88)
A89: II.B1. Outstanding claims - reported claims | B89: =SUM(C89:L89) | W89: =SUM(C89:H89)
A90: II.B2. Outstanding claims - unreported claims | B90: =SUM(C90:L90) | W90: =SUM(C90:H90)
A91: II.B3. Inforce reserves | B91: 23850 | W91: =SUM(C91:H91)
A92: II.B4. Margin over Current Estimate | B92: 3800 | W92: =SUM(C92:H92)
A93: II.B5. Prepaid policyholder premiums | B93: =SUM(C93:L93) | W93: =SUM(C93:H93)
A94: II.B6. Other long term insurance liabilities | B94: =SUM(C94:L94) | W94: =SUM(C94:H94)
A95: II.C. Payables to policyholders, intermediaries & reinsurers (including deposits from) | B95: =SUM(C95:L95) | W95: =SUM(C95:H95) | X95: =SUM(I95:J95)
A96: II.D. Reinsurance liabilities | B96: =SUM(C96:L96) | W96: =SUM(C96:H96) | X96: =SUM(I96:J96)
A97: II.E. Derivative financial instruments | B97: =SUM(C97:L97) | W97: =SUM(C97:H97) | X97: =SUM(I97:J97)
A98: II.F. Repurchase agreements | B98: =SUM(C98:L98) | W98: =SUM(C98:H98) | X98: =SUM(I98:J98)
A99: II.G. Total other liabilities | B99: 2200 | C99: =SUM(C100:C102,C105,C111:C116) | D99: =SUM(D100:D102,D105,D111:D116) | E99: =SUM(E100:E102,E105,E111:E116) | F99: =SUM(F100:F102,F105,F111:F116) | G99: =SUM(G100:G102,G105,G111:G116) | H99: =SUM(H100:H102,H105,H111:H116) | I99: =SUM(I100:I102,I105,I111:I116) | J99: =SUM(J100:J102,J105,J111:J116) | ... L99: =SUM(L100:L102,L105,L111:L116) | N99: =SUM(N100:N102,N105,N111:N116) | P99: =SUM(P100:P102,P105,P111:P116) | R99: =SUM(R100:R102,R105,R111:R116) | T99: =SUM(T100:T102,T105,T111:T116) | W99: =SUM(C99:H99) | X99: =SUM(I99:J99)
A100: II.G1. Interest-bearing financial liabilities issued (non-bank) | B100: =SUM(C100:L100) | W100: =SUM(C100:H100) | X100: =SUM(I100:J100)
A101: II.G2. Bank borrowings | B101: =SUM(C101:L101) | W101: =SUM(C101:H101) | X101: =SUM(I101:J101)
A102: II.G3. Subordinated liabilities | B102: =SUM(B103:B104) | C102: =SUM(C103:C104) | D102: =SUM(D103:D104) | E102: =SUM(E103:E104) | F102: =SUM(F103:F104) | G102: =SUM(G103:G104) | H102: =SUM(H103:H104) | I102: =SUM(I103:I104) | ... L102: =SUM(L103:L104) | N102: =SUM(N103:N104) | P102: =SUM(P103:P104) | R102: =SUM(R103:R104) | T102: =SUM(T103:T104) | W102: =SUM(C102:H102) | X102: =SUM(I102:J102)
A103: II.G3a. Subordinated liabilities not in Eligible Capital Resources | B103: =SUM(C103:L103) | W103: =SUM(C103:H103) | X103: =SUM(I103:J103)
A104: II.G3b. Subordinated liabilities in Eligible Capital Resources | B104: =SUM(C104:L104) | W104: =SUM(C104:H104) | X104: =SUM(I104:J104)
A105: II.G4. Borrowings with / amount due to related parties | B105: 1450 | C105: =SUM(C106:C110) | D105: =SUM(D106:D110) | E105: =SUM(E106:E110) | F105: =SUM(F106:F110) | G105: =SUM(G106:G110) | H105: =SUM(H106:H110) | I105: =SUM(I106:I110) | J105: =SUM(J106:J110) | ... L105: =SUM(L106:L110) | N105: =SUM(N106:N110) | P105: =SUM(P106:P110) | R105: =SUM(R106:R110) | T105: =SUM(T106:T110) | W105: =SUM(C105:H105) | X105: =SUM(I105:J105)
A106: II.G4a. Of which: affiliates / associates | B106: =SUM(C106:L106) | W106: =SUM(C106:H106) | X106: =SUM(I106:J106)
...

Sheet F.LT.1.1 LT CE Summary
A1: F.LT.1.1 Summary of current estimate for long term business
A2: Name of Insurer: | B2: ='Cover Page'!F15
A3: Valuation Date: | B3: 31 Dec 2025
A4: Reporting Period:
A7: (Unit: in HKD thousands)
A8: Column 1 | B8: Column 2 | C8: Column 3 | D8: Column 4 | E8: Column 5 | F8: Column 6 | H8: Column 7 | I8: Column 8 | J8: Column 9 | K8: Column 10
A9: Lines of business classification | B9: Current estimate (excluding the offshore RI business in the case of branches operating in Hong Kong, where offshore RI fund is established) | H9: Current estimate (Gross of RI ceded) (including the offshore RI business)
B10: Deterministic current estimate (Gross of RI ceded) | C10: Time value of options and guarantees (TVOG) | D10: Current estimate (Gross of RI ceded) | E10: RI ceded | F10: Current estimate (Net of RI ceded) | H10: Onshore - Direct | I10: Onshore - Inward RI | J10: Offshore - Direct | K10: Offshore - Inward RI
A11: Total Business | B11: 23850 | C11: =SUM(C30,C12,C24,C27,C42) | D11: 23850 | E11: =SUM(E30,E12,E24,E27,E42) | F11: =D11-E11 | H11: =SUM(H30,H12,H24,H27,H42) | I11: =SUM(I30,I12,I24,I27,I42) | J11: =SUM(J30,J12,J24,J27,J42) | K11: =SUM(K30,K12,K24,K27,K42)
A12: Linked Long Term (Class C) | B12: 0 | C12: =SUM(C13,C16,C19:C23) | D12: 0 | E12: =SUM(E13,E16,E19:E23) | F12: =D12-E12 | H12: =SUM(H13,H16,H19:H23) | I12: =SUM(I13,I16,I19:I23) | J12: =SUM(J13,J16,J19:J23) | K12: =SUM(K13,K16,K19:K23)
A13: Unit Linked | B13: 0 | C13: =SUM(C14:C15) | D13: 0 | E13: =SUM(E14:E15) | F13: =D13-E13 | H13: =SUM(H14:H15) | I13: =SUM(I14:I15) | J13: =SUM(J14:J15) | K13: =SUM(K14:K15)
A14: Unit Linked - Unit Reserves | B14: 0 | D14: 0 | F14: =D14-E14
A15: Unit Linked - Non-Unit Reserves | B15: 0 | D15: 0 | F15: =D15-E15
A16: Indexed Universal Life | B16: =SUM(B17:B18) | C16: =SUM(C17:C18) | D16: =B16+C16 | E16: =SUM(E17:E18) | F16: =D16-E16 | H16: =SUM(H17:H18) | I16: =SUM(I17:I18) | J16: =SUM(J17:J18) | K16: =SUM(K17:K18)
A17: Indexed Universal Life - Account Balance | D17: =B17+C17 | F17: =D17-E17
A18: Indexed Universal Life - Other Reserves | D18: =B18+C18 | F18: =D18-E18
A19: Term | B19: 500 | D19: 500 | F19: =D19-E19
A20: A&H (Medical) | D20: =B20+C20 | F20: =D20-E20
A21: A&H (Critical Illness) | D21: =B21+C21 | F21: =D21-E21
A22: A&H (Accident & Disability) | D22: =B22+C22 | F22: =D22-E22
A23: Others | D23: =B23+C23 | F23: =D23-E23
A24: Retirement Scheme Category I (Class G) | B24: 0 | C24: =SUM(C25:C26) | D24: 0 | E24: =SUM(E25:E26) | F24: =D24-E24 | H24: =SUM(H25:H26) | I24: =SUM(I25:I26) | J24: =SUM(J25:J26) | K24: =SUM(K25:K26)
A25: Class G - Account Balance | D25: =B25+C25 | F25: =D25-E25
A26: Class G - Other Reserves | D26: =B26+C26 | F26: =D26-E26
A27: Retirement Scheme Category II (Class H) | B27: 0 | C27: =SUM(C28:C29) | D27: 0 | E27: =SUM(E28:E29) | F27: =D27-E27 | H27: =SUM(H28:H29) | I27: =SUM(I28:I29) | J27: =SUM(J28:J29) | K27: =SUM(K28:K29)
A28: Class H - Account Balance | D28: =B28+C28 | F28: =D28-E28
A29: Class H - Other Reserves | D29: =B29+C29 | F29: =D29-E29
A30: Participating Business | B30: 18200 | C30: =SUM(C31:C38,C41) | D30: 18200 | E30: =SUM(E31:E38,E41) | F30: =D30-E30 | H30: =SUM(H31:H38,H41) | I30: =SUM(I31:I38,I41) | J30: =SUM(J31:J38,J41) | K30: =SUM(K31:K38,K41)
A31: Whole of Life | B31: 12500 | D31: 12500 | F31: =D31-E31
A32: Endowment | B32: 3800 | D32: 3800 | F32: =D32-E32
A33: Immediate and Deferred Annuities | B33: 1200 | D33: 1200 | F33: =D33-E33
A34: Term | B34: 500 | D34: 500 | F34: =D34-E34
A35: A&H (Medical) | D35: =B35+C35 | F35: =D35-E35
A36: A&H (Critical Illness) | D36: =B36+C36 | F36: =D36-E36
A37: A&H (Accident & Disability) | D37: =B37+C37 | F37: =D37-E37
A38: Policyholders' Funds on Deposit (FOD) | B38: =SUM(B39:B40) | C38: =SUM(C39:C40) | D38: =B38+C38 | E38: =SUM(E39:E40) | F38: =D38-E38 | H38: =SUM(H39:H40) | I38: =SUM(I39:I40) | J38: =SUM(J39:J40) | K38: =SUM(K39:K40)
A39: FOD (Account Balance) | D39: =B39+C39 | F39: =D39-E39
A40: FOD (Other Reserves) | D40: =B40+C40 | F40: =D40-E40
A41: Others | D41: =B41+C41 | F41: =D41-E41
A42: Other Businesses | B42: 5650 | C42: =SUM(C43:C46,C58,C49:C55) | D42: 5650 | E42: =SUM(E43:E46,E58,E49:E55) | F42: =D42-E42 | H42: =SUM(H43:H46,H58,H49:H55) | I42: =SUM(I43:I46,I58,I49:I55) | J42: =SUM(J43:J46,J58,J49:J55) | K42: =SUM(K43:K46,K58,K49:K55)
A43: Whole of Life | B43: 12500 | D43: 12500 | F43: =D43-E43
A44: Endowment | B44: 3800 | D44: 3800 | F44: =D44-E44
A45: Immediate and Deferred Annuities | B45: 1200 | D45: 1200 | F45: =D45-E45
A46: Universal Life | B46: 4100 | C46: =SUM(C47:C48) | D46: 4100 | E46: =SUM(E47:E48) | F46: =D46-E46 | H46: =SUM(H47:H48) | I46: =SUM(I47:I48) | J46: =SUM(J47:J48) | K46: =SUM(K47:K48)
A47: Universal Life (Account Balance) | B47: 4100 | D47: 4100 | F47: =D47-E47
A48: Universal Life (Other Reserves) | B48: 4100 | D48: 4100 | F48: =D48-E48
A49: Term | B49: 500 | D49: 500 | F49: =D49-E49
A50: A&H (Medical) | D50: =B50+C50 | F50: =D50-E50
A51: A&H (Critical Illness) | D51: =B51+C51 | F51: =D51-E51
A52: A&H (Accident & Disability) | D52: =B52+C52 | F52: =D52-E52
A53: Group Life | B53: 1050 | D53: 1050 | F53: =D53-E53
A54: Other Group Business | B54: 500 | D54: 500 | F54: =D54-E54
A55: Policyholders' Funds on Deposit (FOD) | B55: =SUM(B56:B57) | C55: =SUM(C56:C57) | D55: =B55+C55 | E55: =SUM(E56:E57) | F55: =D55-E55 | H55: =SUM(H56:H57) | I55: =SUM(I56:I57) | J55: =SUM(J56:J57) | K55: =SUM(K56:K57)
A56: FOD (Account Balance) | D56: =B56+C56 | F56: =D56-E56
A57: FOD (Other Reserves) | D57: =B57+C57 | F57: =D57-E57
A58: Others | D58: =B58+C58 | F58: =D58-E58
B60: Item 1 Source | C60: Item 1 Value | D60: Item 2 Value | E60: Tolerance | F60: Check
A61: Check (Gross CE of Linked Long Term (Class C) business) | B61: F.LT.1.1 / F.1 | C61: =D12 | D61: ='F.1 EBS'!C91 | E61: 1 | F61: =IF(ABS(D61-C61)<=E61,"OK","Error")
A62: Check (Gross CE of Retirement Scheme Category I (Class G) business) | B62: F.LT.1.1 / F.1 | C62: =D24 | D62: ='F.1 EBS'!D91 | E62: 1 | F62: =IF(ABS(D62-C62)<=E62,"OK","Error")
A63: Check (Gross CE of Retirement Scheme Category II (Class H) business) | B63: F.LT.1.1 / F.1 | C63: =D27 | D63: ='F.1 EBS'!E91 | E63: 1 | F63: =IF(ABS(D63-C63)<=E63,"OK","Error")
A64: Check (Gross CE of Participating business) | B64: F.LT.1.1 / F.1 | C64: =D30 | D64: ='F.1 EBS'!F91 | E64: 1 | F64: =IF(ABS(D64-C64)<=E64,"OK","Error")
A65: Check (Gross CE of Other businesses) | B65: F.LT.1.1 / F.1 | C65: =D42 | D65: ='F.1 EBS'!G91 | E65: 1 | F65: =IF(ABS(D65-C65)<=E65,"OK","Error")
A66: Check (Gross CE of Offshore RI business) | B66: F.LT.1.1 / F.1 | C66: =IF('F.1 EBS'!$H$8="Yes",K11,"N/A") | D66: =IF('F.1 EBS'!$H$8="Yes",'F.1 EBS'!H91,"N/A") | E66: 1 | F66: =IF('F.1 EBS'!$H$8="Yes",IF(ABS(D66-C66)<=E66,"OK","Error"),"N/A")
A67: Check (Total Gross CE) | B67: F.LT.1.1 / F.1 | C67: =SUM(H11:K11) | D67: ='F.1 EBS'!B91 | E67: 1 | F67: =IF(ABS(D67-C67)<=E67,"OK","Error")

Sheet CA.1 CA Summary
B1: CA.1 Summary of capital requirements
B2: Name of Insurer: | C2: ='Cover Page'!F15
B3: Valuation Date: | C3: 31 Dec 2025
B4: Reporting Period:
B6: (Unit: in HKD thousands)
B7: Column 1 | C7: Column 2 | D7: Column 3 | E7: Column 4 | F7: Column 5
C8: As at end of current reporting period (T)
C9: Total | D9: Tier 1 – unlimited | E9: Tier 1 – limited | F9: Tier 2
B10: Eligible capital
B11: Total eligible capital | C11: 11800 | D11: ='CA.R.1 CB composition'!D41 | E11: ='CA.R.1 CB composition'!E57 | F11: ='CA.R.1 CB composition'!E82
B12: Total Tier 1 eligible capital | C12: 11800 | D12: ='CA.R.1 CB composition'!D41 | E12: ='CA.R.1 CB composition'!E57
C14: Diversified PCA/RCA | D14: RCA after additional management action on FDB | E14: RCA before additional management action on FDB
B15: RCA
B16: Market Risk | C16: 1950
B17: Interest Rate Risk | C17: 0 | D17: =MAX(0,IF('CA.P.1.A PCA Summary NetFDB'!$P$6="Without transition", 'CA.P.1.A PCA Summary NetFDB'!N14,'CA.P.1.A PCA Summary NetFDB'!P14)) | E17: =MAX(0,IF('CA.P.2 PCA Summary GrossFDB'!$P$6="Without transition", 'CA.P.2 PCA Summary GrossFDB'!N14,'CA.P.2 PCA Summary GrossFDB'!P14))
B18: Credit Spread Risk | C18: 0 | D18: =MAX(0,IF('CA.P.1.A PCA Summary NetFDB'!$P$6="Without transition", 'CA.P.1.A PCA Summary NetFDB'!N15,'CA.P.1.A PCA Summary NetFDB'!P15)) | E18: =MAX(0,IF('CA.P.2 PCA Summary GrossFDB'!$P$6="Without transition", 'CA.P.2 PCA Summary GrossFDB'!N15,'CA.P.2 PCA Summary GrossFDB'!P15))
B19: Equity Risk | C19: 0 | D19: =MAX(0,IF('CA.P.1.A PCA Summary NetFDB'!$P$6="Without transition", 'CA.P.1.A PCA Summary NetFDB'!N16,'CA.P.1.A PCA Summary NetFDB'!P16)) | E19: =MAX(0,IF('CA.P.2 PCA Summary GrossFDB'!$P$6="Without transition", 'CA.P.2 PCA Summary GrossFDB'!N16,'CA.P.2 PCA Summary GrossFDB'!P16))
B20: Property Risk | C20: 0 | D20: =MAX(0,IF('CA.P.1.A PCA Summary NetFDB'!$P$6="Without transition", 'CA.P.1.A PCA Summary NetFDB'!N17,'CA.P.1.A PCA Summary NetFDB'!P17)) | E20: =MAX(0,IF('CA.P.2 PCA Summary GrossFDB'!$P$6="Without transition", 'CA.P.2 PCA Summary GrossFDB'!N17,'CA.P.2 PCA Summary GrossFDB'!P17))
B21: Currency Risk | C21: 0 | D21: =MAX(0,IF('CA.P.1.A PCA Summary NetFDB'!$P$6="Without transition", 'CA.P.1.A PCA Summary NetFDB'!N18,'CA.P.1.A PCA Summary NetFDB'!P18)) | E21: =MAX(0,IF('CA.P.2 PCA Summary GrossFDB'!$P$6="Without transition", 'CA.P.2 PCA Summary GrossFDB'!N18,'CA.P.2 PCA Summary GrossFDB'!P18))
B22: Life Insurance Risk | C22: 3100
B23: Mortality Risk | C23: 820 | D23: =MAX(0,IF('CA.P.1.A PCA Summary NetFDB'!$P$6="Without transition", 'CA.P.1.A PCA Summary NetFDB'!N22,'CA.P.1.A PCA Summary NetFDB'!P22)) | E23: =MAX(0,IF('CA.P.2 PCA Summary GrossFDB'!$P$6="Without transition", 'CA.P.2 PCA Summary GrossFDB'!N22,'CA.P.2 PCA Summary GrossFDB'!P22))
B24: Longevity Risk | C24: 90 | D24: =MAX(0,IF('CA.P.1.A PCA Summary NetFDB'!$P$6="Without transition", 'CA.P.1.A PCA Summary NetFDB'!N23,'CA.P.1.A PCA Summary NetFDB'!P23)) | E24: =MAX(0,IF('CA.P.2 PCA Summary GrossFDB'!$P$6="Without transition", 'CA.P.2 PCA Summary GrossFDB'!N23,'CA.P.2 PCA Summary GrossFDB'!P23))
B25: Life Catastrophe Risk | C25: 480 | D25: =MAX(0,IF('CA.P.1.A PCA Summary NetFDB'!$P$6="Without transition", 'CA.P.1.A PCA Summary NetFDB'!N24,'CA.P.1.A PCA Summary NetFDB'!P24)) | E25: =MAX(0,IF('CA.P.2 PCA Summary GrossFDB'!$P$6="Without transition", 'CA.P.2 PCA Summary GrossFDB'!N24,'CA.P.2 PCA Summary GrossFDB'!P24))
B26: Morbidity Risk | C26: 200 | D26: =MAX(0,IF('CA.P.1.A PCA Summary NetFDB'!$P$6="Without transition", 'CA.P.1.A PCA Summary NetFDB'!N25,'CA.P.1.A PCA Summary NetFDB'!P25)) | E26: =MAX(0,IF('CA.P.2 PCA Summary GrossFDB'!$P$6="Without transition", 'CA.P.2 PCA Summary GrossFDB'!N25,'CA.P.2 PCA Summary GrossFDB'!P25))
B27: Expense Risk | C27: 640 | D27: =MAX(0,IF('CA.P.1.A PCA Summary NetFDB'!$P$6="Without transition", 'CA.P.1.A PCA Summary NetFDB'!N26,'CA.P.1.A PCA Summary NetFDB'!P26)) | E27: =MAX(0,IF('CA.P.2 PCA Summary GrossFDB'!$P$6="Without transition", 'CA.P.2 PCA Summary GrossFDB'!N26,'CA.P.2 PCA Summary GrossFDB'!P26))
B28: Lapse Risk | C28: 870 | D28: =MAX(0,IF('CA.P.1.A PCA Summary NetFDB'!$P$6="Without transition", 'CA.P.1.A PCA Summary NetFDB'!N27,'CA.P.1.A PCA Summary NetFDB'!P27)) | E28: =MAX(0,IF('CA.P.2 PCA Summary GrossFDB'!$P$6="Without transition", 'CA.P.2 PCA Summary GrossFDB'!N27,'CA.P.2 PCA Summary GrossFDB'!P27))
B29: General Insurance Risk | C29: 0
B30: General Insurance Risk (excluding Mortgage Insurance) | C30: 0
B31: Reserve & Premium Risk | D31: =MAX(0,IF('CA.P.1.A PCA Summary NetFDB'!$P$6="Without transition", 'CA.P.1.A PCA Summary NetFDB'!N32,'CA.P.1.A PCA Summary NetFDB'!P32)) | E31: =MAX(0,IF('CA.P.2 PCA Summary GrossFDB'!$P$6="Without transition", 'CA.P.2 PCA Summary GrossFDB'!N32,'CA.P.2 PCA Summary GrossFDB'!P32))
B32: Natural Catastrophe Risk | D32: =MAX(0,IF('CA.P.1.A PCA Summary NetFDB'!$P$6="Without transition", 'CA.P.1.A PCA Summary NetFDB'!N33,'CA.P.1.A PCA Summary NetFDB'!P33)) | E32: =MAX(0,IF('CA.P.2 PCA Summary GrossFDB'!$P$6="Without transition", 'CA.P.2 PCA Summary GrossFDB'!N33,'CA.P.2 PCA Summary GrossFDB'!P33))
B33: Man-made Non-systemic Catastrophe Risk | D33: =MAX(0,IF('CA.P.1.A PCA Summary NetFDB'!$P$6="Without transition", 'CA.P.1.A PCA Summary NetFDB'!N34,'CA.P.1.A PCA Summary NetFDB'!P34)) | E33: =MAX(0,IF('CA.P.2 PCA Summary GrossFDB'!$P$6="Without transition", 'CA.P.2 PCA Summary GrossFDB'!N34,'CA.P.2 PCA Summary GrossFDB'!P34))
B34: Man-made Systemic Catastrophe Risk | D34: =MAX(0,IF('CA.P.1.A PCA Summary NetFDB'!$P$6="Without transition", 'CA.P.1.A PCA Summary NetFDB'!N35,'CA.P.1.A PCA Summary NetFDB'!P35)) | E34: =MAX(0,IF('CA.P.2 PCA Summary GrossFDB'!$P$6="Without transition", 'CA.P.2 PCA Summary GrossFDB'!N35,'CA.P.2 PCA Summary GrossFDB'!P35))
B35: Mortgage Insurance Risk | C35: 0
B36: Counterparty Default and Other Risk | C36: 180
B37: PCA before Operational Risk (before LAC cap) | C37: 4870
B38: Operational Risk | C38: 520
B39: PCA (before LAC cap) | C39: 5390
B40: Adjustment for LAC cap | C40: -900
B41: Adjustment for tax effect on deferred tax assets | C41: -140
B42: PCA | C42: 4350
B43: Any other items which the IA may specify to adjust (for example section 10 adjustment) | C43: 0
B44: PCA (after specified adjustment where applicable) | C44: 4350
B46: MCA | C46: 2175
B47: Any other items which the IA may specify to adjust (for example section 10 adjustment) | C47: 0
... B53: Ratio of Tier 1 Eligible capital to PCA (in %) | C53: 2.712644
